core/__init__.py
core/launchers.py
core/metrics.py
core/recording.py
core/sampling.py
doctests/__init__.py
doctests/quick_tests.py
ui/__init__.py
ui/flask/__init__.py
ui/flask/views.py
ui/flask/templates/layout.html
ui/flask/templates/ox_prof_err.html
ui/flask/templates/ox_prof_intro.html
ui/flask/templates/ox_prof_layout.html
ui/flask/templates/ox_prof_msg.html
ui/flask/templates/ox_prof_rinfo.html
ui/flask/templates/ox_prof_status.html
ox_profile-0.2.11.dist-info/LICENSE
ox_profile-0.2.11.dist-info/METADATA
ox_profile-0.2.11.dist-info/WHEEL
ox_profile-0.2.11.dist-info/top_level.txt
ox_profile-0.2.11.dist-info/RECORD
