Metadata-Version: 2.1
Name: ox_profile
Version: 0.2.11
Summary: Tools for statistical profiling.
Author-email: Emin Martinian <emin.martinian@gmail.com>
License: MIT License
Project-URL: Homepage, https://github.com/emin63/ox_profile
Project-URL: Issues, https://github.com/emin63/ox_profile/issues
Classifier: Development Status :: 3 - Alpha
Classifier: Intended Audience :: Developers
Classifier: Programming Language :: Python :: 3
Classifier: Operating System :: OS Independent
Classifier: License :: OSI Approved :: MIT License
Requires-Python: >=3.1
License-File: LICENSE
